approval_workflow/__init__.py
approval_workflow/admin.py
approval_workflow/apps.py
approval_workflow/choices.py
approval_workflow/handlers.py
approval_workflow/models.py
approval_workflow/services.py
approval_workflow/utils.py
approval_workflow/management/__init__.py
approval_workflow/management/commands/__init__.py
approval_workflow/management/commands/setup_approval_forms.py
approval_workflow/migrations/0001_initial.py
approval_workflow/migrations/0002_approvalinstance_approval_type.py
approval_workflow/migrations/0003_enhanced_features_combined.py
approval_workflow/migrations/__init__.py
approval_workflow/tests/__init__.py
approval_workflow/tests/conftest.py
approval_workflow/tests/test_approval_types.py
approval_workflow/tests/test_current_approval_behavior.py
approval_workflow/tests/test_delegation_escalation.py
approval_workflow/tests/test_enhanced_role_strategies.py
approval_workflow/tests/test_extend_flow.py
approval_workflow/tests/test_flow_creation.py
approval_workflow/tests/test_handlers.py
approval_workflow/tests/test_instance_keyword_fix.py
approval_workflow/tests/test_performance.py
approval_workflow/tests/test_role_based_approvals.py
approval_workflow/tests/test_role_permissions.py
approval_workflow/tests/test_sla_features.py
approval_workflow/tests/test_utilities.py
django_approval_workflow-0.9.0.dist-info/licenses/LICENSE
django_approval_workflow-0.9.0.dist-info/METADATA
django_approval_workflow-0.9.0.dist-info/WHEEL
django_approval_workflow-0.9.0.dist-info/top_level.txt
django_approval_workflow-0.9.0.dist-info/RECORD
