Metadata-Version: 2.4
Name: django-approval-workflow
Version: 0.9.0
Summary: A powerful, flexible Django package for implementing dynamic multi-step approval workflows
Author-email: Mohamed Salah <info@codxi.com>
License-Expression: MIT
Project-URL: Homepage, https://github.com/Codxi-Co/django-approval-workflow
Project-URL: Repository, https://github.com/Codxi-Co/django-approval-workflow.git
Project-URL: Documentation, https://github.com/Codxi-Co/django-approval-workflow#readme
Project-URL: Bug Tracker, https://github.com/Codxi-Co/django-approval-workflow/issues
Classifier: Development Status :: 5 - Production/Stable
Classifier: Environment :: Web Environment
Classifier: Framework :: Django
Classifier: Framework :: Django :: 4.0
Classifier: Framework :: Django :: 4.1
Classifier: Framework :: Django :: 4.2
Classifier: Framework :: Django :: 5.0
Classifier: Framework :: Django :: 5.1
Classifier: Framework :: Django :: 5.2
Classifier: Framework :: Django :: 6.0
Classifier: Intended Audience :: Developers
Classifier: Operating System :: OS Independent
Classifier: Programming Language :: Python
Classifier: Programming Language :: Python :: 3
Classifier: Programming Language :: Python :: 3.10
Classifier: Programming Language :: Python :: 3.11
Classifier: Programming Language :: Python :: 3.12
Classifier: Programming Language :: Python :: 3.14
Classifier: Topic :: Internet :: WWW/HTTP
Classifier: Topic :: Internet :: WWW/HTTP :: Dynamic Content
Classifier: Topic :: Software Development :: Libraries :: Python Modules
Requires-Python: >=3.10
License-File: LICENSE
Requires-Dist: Django<7.0,>=4.0
Requires-Dist: django-mptt>=0.16.0
Provides-Extra: api
Requires-Dist: djangorestframework>=3.15.0; extra == "api"
Provides-Extra: dev
Requires-Dist: pytest>=7.0.0; extra == "dev"
Requires-Dist: pytest-django>=4.5.0; extra == "dev"
Requires-Dist: factory-boy>=3.2.0; extra == "dev"
Requires-Dist: coverage>=7.0.0; extra == "dev"
Requires-Dist: black>=23.0.0; extra == "dev"
Requires-Dist: isort>=5.0.0; extra == "dev"
Requires-Dist: flake8>=6.0.0; extra == "dev"
Dynamic: license-file
